{
    "user_id": "testuser",
    "display_name": "testuser",
    "email": "",
    "suspended": 0,
    "max_buckets": 1000,
    "auid": 0,
    "subusers": [],
    "keys": [
        {
            "user": "testuser",
            "access_key": "75FP188E40PGB88UU12D",
            "secret_key": "IryhO8VZDUBkvVkmG8qgcPgG6sOYUs1sRAdFRjgc"
        }
    ],
    "swift_keys": [],
    "caps": [],
    "op_mask": "read, write, delete",
    "default_placement": "",
    "placement_tags": [],
    "bucket_quota": {
        "enabled": false,
        "max_size_kb": -1,
        "max_objects": -1
    },
    "user_quota": {
        "enabled": false,
        "max_size_kb": -1,
        "max_objects": -1
    },
    "temp_url_keys": []
}